vkstartii.py
vkstartii-0.1.0.dist-info/WHEEL
vkstartii-0.1.0.dist-info/METADATA
vkstartii-0.1.0.dist-info/RECORD
