Metadata-Version: 2.1
Name: vkstartii
Version: 0.1.0
Summary: 
Author: LooPeKa
Author-email: loudmaks10@gmail.com
Requires-Python: >=3.8,<4.0
Classifier: Programming Language :: Python :: 3
Classifier: Programming Language :: Python :: 3.8
Requires-Dist: hashlib (>=20081119,<20081120)
Requires-Dist: requests (>=2.23.0,<3.0.0)
Requires-Dist: vk_api (>=11.8.0,<12.0.0)
